ctakes_parser/__init__.py
ctakes_parser/ctakes_parser.py
ctakes_parser/helpers.py
ctakes_parser-0.1.0.dist-info/LICENSE
ctakes_parser-0.1.0.dist-info/METADATA
ctakes_parser-0.1.0.dist-info/WHEEL
ctakes_parser-0.1.0.dist-info/top_level.txt
ctakes_parser-0.1.0.dist-info/RECORD
