Metadata-Version: 2.1
Name: ctakes-parser
Version: 0.1.0
Summary: Python 3 port of CTakes output parser.
Home-page: https://github.com/titu1994/PyCTakesParser
Author: Somshubra Majumdar
Author-email: titu1994@gmail.com
License: MIT
Download-URL: https://github.com/titu1994/PyCTakesParser
Platform: UNKNOWN
Classifier: Programming Language :: Python :: 3
Classifier: Programming Language :: Python :: 3.5
Classifier: Programming Language :: Python :: 3.6
Classifier: Programming Language :: Python :: 3.7
Classifier: License :: OSI Approved :: MIT License
Classifier: Operating System :: OS Independent
Classifier: Topic :: Software Development :: Libraries
Classifier: Topic :: Software Development :: Libraries :: Python Modules
Requires-Python: >=3.0.0
Requires-Dist: pandas
Requires-Dist: lxml
Provides-Extra: test
Requires-Dist: pytest ; extra == 'test'
